tiggy/__init__.py
tiggy/envs/__init__.py
tiggy/envs/tic_tac_toe.py
tiggy/rl_framework/__init__.py
tiggy/rl_framework/trainer.py
tiggy/rl_models/__init__.py
tiggy/rl_models/models.py
tiggy/rl_utils/__init__.py
tiggy/rl_utils/utils.py
tiggy/transformers/__init__.py
tiggy/transformers/transformer_layers.py
tiggy/transformers/transformer_models.py
tiggy-0.5.dist-info/LICENSE
tiggy-0.5.dist-info/METADATA
tiggy-0.5.dist-info/WHEEL
tiggy-0.5.dist-info/top_level.txt
tiggy-0.5.dist-info/RECORD
