Metadata-Version: 2.1
Name: tiggy
Version: 0.5
Summary: tiggy
Home-page: UNKNOWN
License: GPL v3.0
Platform: UNKNOWN
License-File: LICENSE
Requires-Dist: numpy
Requires-Dist: einops
Requires-Dist: torch
Requires-Dist: numba
